python_carrier_infinity/__about__.py
python_carrier_infinity/__init__.py
python_carrier_infinity/api.py
python_carrier_infinity/config.py
python_carrier_infinity/status.py
python_carrier_infinity/system.py
python_carrier_infinity/types.py
python_carrier_infinity/gql_schemas/__init__.py
python_carrier_infinity/gql_schemas/get_config.py
python_carrier_infinity/gql_schemas/get_status.py
python_carrier_infinity/gql_schemas/get_user.py
python_carrier_infinity/gql_schemas/update_activity.py
python_carrier_infinity/gql_schemas/update_config.py
python_carrier_infinity/gql_schemas/update_zone_config.py
python_carrier_infinity-0.0.3.dist-info/METADATA
python_carrier_infinity-0.0.3.dist-info/WHEEL
python_carrier_infinity-0.0.3.dist-info/licenses/LICENSE.txt
python_carrier_infinity-0.0.3.dist-info/RECORD
