Metadata-Version: 2.1
Name: python-carrier-infinity
Version: 0.0.3
Summary: A Python library for accessing Carrier Infinity thermostats
Project-URL: Documentation, https://github.com/mileswu/python-carrier-infinity#readme
Project-URL: Issues, https://github.com/mileswu/python-carrier-infinity/issues
Project-URL: Source, https://github.com/mileswu/python-carrier-infinity
Author-email: "@mileswu" <mileswu@users.noreply.github.com>
License-Expression: MIT
License-File: LICENSE.txt
Classifier: Development Status :: 4 - Beta
Classifier: Programming Language :: Python
Classifier: Programming Language :: Python :: 3.7
Classifier: Programming Language :: Python :: 3.8
Classifier: Programming Language :: Python :: 3.9
Classifier: Programming Language :: Python :: 3.10
Classifier: Programming Language :: Python :: 3.11
Classifier: Programming Language :: Python :: Implementation :: CPython
Classifier: Programming Language :: Python :: Implementation :: PyPy
Requires-Python: >=3.7
Requires-Dist: aiohttp~=3.8
Requires-Dist: oauthlib~=3.2
Requires-Dist: python-dateutil~=2.8
